pah_gui/__init__.py
pah_gui-1.3.2.dist-info/METADATA
pah_gui-1.3.2.dist-info/WHEEL
pah_gui-1.3.2.dist-info/RECORD
