Metadata-Version: 2.4
Name: pah-gui
Version: 1.3.2
Requires-Dist: pah-core==1.3.2
Requires-Dist: streamlit>=1.45.1
